{
    "weeks": [
        {
            "week": "Week 1",
            "links": [
                {
                    "url": "week01/holygrail.html",
                    "title": "HG Layout"
                },
                {
                    "url": "week01/media-query.html",
                    "title": "mQueries"
                }
            ]

            "week2": "Week 2",
            "links2": [
                {
                    "url": "week01/holygrail.html",
                    "title": "HG Layout"
                },
                {
                    "url": "week01/media-query.html",
                    "title": "mQueries"
                }
            ]
        }
    ]
}